NT.py-4.3.4.data/data/scrapers.json
nitrotype/__init__.py
nitrotype/scrapers.json
NT.py-4.3.4.dist-info/LICENSE
NT.py-4.3.4.dist-info/METADATA
NT.py-4.3.4.dist-info/WHEEL
NT.py-4.3.4.dist-info/top_level.txt
NT.py-4.3.4.dist-info/RECORD
