Metadata-Version: 2.1
Name: NT.py
Version: 4.3.4
Summary: A package to use the nitrotype api and get player or team stats
Home-page: https://github.com/adl212/NT.py
Author-email: emailforpythoncoding@gmail.com
Classifier: Programming Language :: Python :: 3
Classifier: License :: OSI Approved :: MIT License
Classifier: Operating System :: OS Independent
Requires-Python: >=3.6
License-File: LICENSE
Requires-Dist: cloudscraper
Requires-Dist: jsonpickle
